{"directed": true, "multigraph": false, "graph": {}, "elements": {"nodes": [{"data": {"name": "<img src=\"extension/images/icon_128.png\" width=\"45\" align=\"left\"> StumbleUponAwesome", "node_type": 1, "id": "186e2645b9c98d6795cb163722f143f756560daea2f58675af29a7168fbdf671"}}, {"data": {"name": "res-b6cd7bc", "data": {"text": "An *awesome* internet discovery button, for developers, tech and science lovers. ", "link": ""}, "resource_type": 1, "node_type": 2, "id": "b6cd7bc83dd889aa5ea78126f53bb8a1d558cd92288cadfd66dc165094195c70"}}, {"data": {"name": "res-4abfffa", "data": {"text": "There are 41,299 unique sites from 542 awesome lists on Github from kind contributors. There's some hidden gems waiting in there \ud83d\udc8e . ", "link": ""}, "resource_type": 1, "node_type": 2, "id": "4abfffa2a2dd330e7403f4689fefd36cede26b17e969346c2bb4404326bc8cda"}}, {"data": {"name": "res-cb3f91d", "data": {"text": "---", "link": ""}, "resource_type": 1, "node_type": 2, "id": "cb3f91d54eee30e53e35b2b99905f70f169ed549fd78909d3dac2defc9ed8d3b"}}, {"data": {"name": "How to use it:", "node_type": 1, "id": "468ef0065ba2455fcf68a869e4922479423b4974f06645f8faf6fda629a7e37e"}}, {"data": {"name": "res-8e14be0", "data": {"text": "*To stumble:** Simply click on the \u26a1\ufe0f extension button \u2192 go to a new awesome site!", "link": ""}, "resource_type": 1, "node_type": 2, "id": "8e14be0d6642de9a2ba0cfe2ff1558c2b976f1896c5068946978c7db5351f04e"}}, {"data": {"name": "res-d8156ba", "data": {"text": "--", "link": ""}, "resource_type": 1, "node_type": 2, "id": "d8156bae0c4243d3742fc4e9774d8aceabe0410249d720c855f98afc88ff846c"}}, {"data": {"name": "\uaa5c Introducing: The Rabbit Hole", "node_type": 1, "id": "903c61e1b15a5d9bcaef4a5485ad35569c722efce6e93ed89e6a550df9dcd291"}}, {"data": {"name": "res-8e8c0c3", "data": {"text": "One minute you're casually reading the news, the next you've read so much about `random topic` you might as well do a TED talk. <br/>", "link": ""}, "resource_type": 1, "node_type": 2, "id": "8e8c0c3583af6aa125d589281e60daf639131557d362b9688223188530340918"}}, {"data": {"name": "res-765f2fa", "data": {"text": "So why not embrace it, by having a fancy button for it, _obviously_. ", "link": ""}, "resource_type": 1, "node_type": 2, "id": "765f2faf304a7250d1073e39b4f7e453dab390d95a3c16415b84eca04cb2070f"}}, {"data": {"name": "res-e1a6880", "data": {"text": "*Stay stumblin' on the same topic,** or exit back to random mode.<br/>", "link": ""}, "resource_type": 1, "node_type": 2, "id": "e1a68800899101c23276575626e91253827f4b75f61cdd0cbc85a496bf0c6258"}}, {"data": {"name": "Setup", "node_type": 1, "id": "7013af4c42fe43802a9e8b0affc4f521fcd126160569969fb2ec09e1b7c422b1"}}, {"data": {"name": "Development", "node_type": 1, "id": "21b6a798321a49f75b9c3827fa3cfdb7efe2c4e05c3d13aefe1c825b9774a158"}}, {"data": {"name": "res-714785e", "data": {"text": "Here's some of the things I'd like to build out for this extension. However the main one right now is simply to curate the links as good as I can, add more data sources and make sure the pages are a good mix of interesting, useful, fun and exciting. ", "link": ""}, "resource_type": 1, "node_type": 2, "id": "714785ed1cf74b205931b71a9031204b2ccd60ffc8fceeb1618bf90acbf7c134"}}, {"data": {"name": "res-455e54f", "data": {"text": "[ ] Feedback mechanism for good/bad links", "link": ""}, "resource_type": 1, "node_type": 2, "id": "455e54f80266710871e2a2f8a77ca18c910e4509a0fd8a2cd1ea243faa08e5d6"}}, {"data": {"name": "res-b2b5a7a", "data": {"text": "[ ] Favourite 'gems' to bookmark folder", "link": ""}, "resource_type": 1, "node_type": 2, "id": "b2b5a7a9f78ecb2389b8dcfaa67b16b3dba32eabd80026420ed6b76f5f737eec"}}, {"data": {"name": "res-62a1eb0", "data": {"text": "[ ] Basic stats", "link": ""}, "resource_type": 1, "node_type": 2, "id": "62a1eb046b3ff7b2b55ed1758aee82c87b4d4d7d6ba91846eb55470bcaba4cc7"}}, {"data": {"name": "res-320c64a", "data": {"text": "[ ] Categories", "link": ""}, "resource_type": 1, "node_type": 2, "id": "320c64ae7957fab2b92f45834b09f502a4a9dca20b16b4471cafbb3c479ba96e"}}, {"data": {"name": "res-2ec7476", "data": {"text": "[x] Rabbit hole feature (stay on the same topic).", "link": ""}, "resource_type": 1, "node_type": 2, "id": "2ec74762990c76fb720f9c93872b9066e56928b1484c89d60b500e4be6a26574"}}, {"data": {"name": "res-46577bb", "data": {"text": "[x] Firefox support", "link": ""}, "resource_type": 1, "node_type": 2, "id": "46577bbdc25ef8658dcd6465951bc89d5d7326a461e43df8d0ff42b27f61d98c"}}, {"data": {"name": "res-7c6b1c6", "data": {"text": "[ ] Safari support", "link": ""}, "resource_type": 1, "node_type": 2, "id": "7c6b1c686ce84e854de71e324548966e1cd526b2a57d8b77e6ac63452ffd87d3"}}, {"data": {"name": "res-5b8f390", "data": {"text": "*[\u2192 Changelog](CHANGELOG.md)**", "link": ""}, "resource_type": 1, "node_type": 2, "id": "5b8f39054fe0c7e863376eea7ef1f02fec72f9ffe3383187004725921b521b84"}}, {"data": {"name": "A note about permissions", "node_type": 1, "id": "b1141e0ba9ecac9c32e4cbe29ebcfbe6e9782d4735ec7e8ab9a8ee935ccc5f08"}}, {"data": {"name": "res-5950c2d", "data": {"text": "This extension requires the `<all_urls>` permission, in order to show the overlay UI on every stumble page that you visit. It does not access data on these sites. There is no tracking, or analytics of any kind, and state is only stored locally. ", "link": ""}, "resource_type": 1, "node_type": 2, "id": "5950c2d690b96aa41766ce98033b3df7b1db39eb6f6fdfde64fa7b8857d8da50"}}, {"data": {"name": "Credit to the curators \u2714", "node_type": 1, "id": "aab01ebdcc700e43f43a775b36c90ccc28d095743d70eb9672b6320d424fc131"}}, {"data": {"name": "res-c79bba4", "data": {"text": "This extension is made possible by awesome people curating the internet:", "link": ""}, "resource_type": 1, "node_type": 2, "id": "c79bba4f6a73a3548585465aa9bb626268fb9e9d73ddb07c85f9d4bc490b6017"}}, {"data": {"name": "res-4ea0b31", "data": {"text": "sindresorhus/awesome", "link": "https://github.com/sindresorhus/awesome"}, "resource_type": 2, "node_type": 2, "id": "4ea0b317c36b2cf0a457d51b140193e477a17fc2dc44d52924a5fc0e50515438"}}, {"data": {"name": "A note about the dataset", "node_type": 1, "id": "55236c2756ace8d14a8838bc2462266027f68c056200770cd1e647d834f1d9f6"}}, {"data": {"name": "res-57f06c0", "data": {"text": "It's completely local - you can find it under [/extension/data](./extension/data). It's generated with [awesome_scraper.py](./scraper/awesome_scraper.py). ", "link": ""}, "resource_type": 1, "node_type": 2, "id": "57f06c08351561e85771c51d991e1f8deea01f4077f033ec98ba402b8ec3d971"}}, {"data": {"name": "## Maintaining quality", "node_type": 1, "id": "dc8ab306a30e4f957e469cbe4e231ba74230676c05e0034851215ef64ad4864f"}}, {"data": {"name": "res-316d0a6", "data": {"text": "To make sure that every link works and is relevant, the dataset is cleaned. Any dead or broken links are removed, as well as links to CI pipelines, recursive links, donation links, etc. This is done with the cleanup functions in [utils.py](./scraper/utils.py). Running this script can take a few hours on a slow connection.", "link": ""}, "resource_type": 1, "node_type": 2, "id": "316d0a6276eaea2f62cdcb17c6a73a1035ae156ff437d899bc90e3529e0928df"}}, {"data": {"name": "## Broken links", "node_type": 1, "id": "ec753afed0fd7de2a678563f5ad4cf0c8251d9cd1ed7fed115fef97584686caf"}}, {"data": {"name": "res-8823021", "data": {"text": "After removing from the dataset, a record of dead or broken links (those with 404, SSL, other server errors) is saved in [these text files](./extension/data/broken-urls) after every scrape. ", "link": ""}, "resource_type": 1, "node_type": 2, "id": "88230214c5a9f3fbadcd92618a619fe106e627cc66fe9be7347f3c3e26e0e84d"}}, {"data": {"name": "# Contribute", "node_type": 1, "id": "07515d68646d454c3cc8ef5de976b88f8ff0d6d0f3ef0b18547d721e724220f8"}}], "edges": [{"data": {"id": "59728188ea15c90093c4a0b8f945a91865e81876439eeb840c70b7d5ddf22430", "source": "b6cd7bc83dd889aa5ea78126f53bb8a1d558cd92288cadfd66dc165094195c70", "target": "186e2645b9c98d6795cb163722f143f756560daea2f58675af29a7168fbdf671"}}, {"data": {"id": "0aaa3c0e393f9545c326af67051ef87974e8660738ace7e78b62025ba3a6f7f9", "source": "4abfffa2a2dd330e7403f4689fefd36cede26b17e969346c2bb4404326bc8cda", "target": "186e2645b9c98d6795cb163722f143f756560daea2f58675af29a7168fbdf671"}}, {"data": {"id": "b720bfdd18ae03858fde4d032999a677f47465019a1d6f7b944c8280129ec58f", "source": "cb3f91d54eee30e53e35b2b99905f70f169ed549fd78909d3dac2defc9ed8d3b", "target": "186e2645b9c98d6795cb163722f143f756560daea2f58675af29a7168fbdf671"}}, {"data": {"id": "92f4538f239ef146ff6d2ec80ac3c89ad21886f8eaa275fd84873de474fb0fa9", "source": "468ef0065ba2455fcf68a869e4922479423b4974f06645f8faf6fda629a7e37e", "target": "186e2645b9c98d6795cb163722f143f756560daea2f58675af29a7168fbdf671"}}, {"data": {"id": "f285df5b2671b509c51371087ff6fb9318c48e1659ff2a65afa4bba28de6b472", "source": "8e14be0d6642de9a2ba0cfe2ff1558c2b976f1896c5068946978c7db5351f04e", "target": "468ef0065ba2455fcf68a869e4922479423b4974f06645f8faf6fda629a7e37e"}}, {"data": {"id": "1d04aa96af51420a4c67549ade579754e553c15e123ac8929919008439873a95", "source": "d8156bae0c4243d3742fc4e9774d8aceabe0410249d720c855f98afc88ff846c", "target": "468ef0065ba2455fcf68a869e4922479423b4974f06645f8faf6fda629a7e37e"}}, {"data": {"id": "df706a7d6cf77603601fede40b864a211031f56432c198a8924a48996eb9a14b", "source": "d8156bae0c4243d3742fc4e9774d8aceabe0410249d720c855f98afc88ff846c", "target": "903c61e1b15a5d9bcaef4a5485ad35569c722efce6e93ed89e6a550df9dcd291"}}, {"data": {"id": "2f05f731e6e88c89ad0c7e911f94a79a5d12639e3232a17e5dde8c268e1d71ef", "source": "903c61e1b15a5d9bcaef4a5485ad35569c722efce6e93ed89e6a550df9dcd291", "target": "468ef0065ba2455fcf68a869e4922479423b4974f06645f8faf6fda629a7e37e"}}, {"data": {"id": "80c2b4249f4ae194bb1b5e8e63f86a89101f8401b1abb3f4d679159ad5272e14", "source": "8e8c0c3583af6aa125d589281e60daf639131557d362b9688223188530340918", "target": "903c61e1b15a5d9bcaef4a5485ad35569c722efce6e93ed89e6a550df9dcd291"}}, {"data": {"id": "9f8b1eafe266d7713f803facda2dec26795efab8c72797cf2d0d5c368eb48f43", "source": "765f2faf304a7250d1073e39b4f7e453dab390d95a3c16415b84eca04cb2070f", "target": "903c61e1b15a5d9bcaef4a5485ad35569c722efce6e93ed89e6a550df9dcd291"}}, {"data": {"id": "a9df0291d51159fd4b4ef9cdd67bdecc60fc6e0092a5075d2d0cc13d0fa75ffc", "source": "e1a68800899101c23276575626e91253827f4b75f61cdd0cbc85a496bf0c6258", "target": "903c61e1b15a5d9bcaef4a5485ad35569c722efce6e93ed89e6a550df9dcd291"}}, {"data": {"id": "f3239b9f575a6af427ba2dc92349cb7c30c95bfb5abddfce735b1aa037653278", "source": "7013af4c42fe43802a9e8b0affc4f521fcd126160569969fb2ec09e1b7c422b1", "target": "468ef0065ba2455fcf68a869e4922479423b4974f06645f8faf6fda629a7e37e"}}, {"data": {"id": "abf1f457d773bd456c4b1f95ac13b7b0327c2fce03e3f9ee4f33b94e3c77f43d", "source": "21b6a798321a49f75b9c3827fa3cfdb7efe2c4e05c3d13aefe1c825b9774a158", "target": "468ef0065ba2455fcf68a869e4922479423b4974f06645f8faf6fda629a7e37e"}}, {"data": {"id": "87f77ddd02354ef6ad6c7fae20c7eb453f7b18d37fb144025a09357e7fde0905", "source": "714785ed1cf74b205931b71a9031204b2ccd60ffc8fceeb1618bf90acbf7c134", "target": "21b6a798321a49f75b9c3827fa3cfdb7efe2c4e05c3d13aefe1c825b9774a158"}}, {"data": {"id": "32e3e5463cd9b91ba2ea5ccc4f46cceabf637dc6a69c0d2087d1309fd7086575", "source": "455e54f80266710871e2a2f8a77ca18c910e4509a0fd8a2cd1ea243faa08e5d6", "target": "21b6a798321a49f75b9c3827fa3cfdb7efe2c4e05c3d13aefe1c825b9774a158"}}, {"data": {"id": "242ba7d6bf49ddf38b4103cd4549befd2536a09046660b2e7786566c9232260b", "source": "b2b5a7a9f78ecb2389b8dcfaa67b16b3dba32eabd80026420ed6b76f5f737eec", "target": "21b6a798321a49f75b9c3827fa3cfdb7efe2c4e05c3d13aefe1c825b9774a158"}}, {"data": {"id": "bd5bcac493e43e750bb6711f504ae7b8e385937942f6c7c64a253a6dfb330124", "source": "62a1eb046b3ff7b2b55ed1758aee82c87b4d4d7d6ba91846eb55470bcaba4cc7", "target": "21b6a798321a49f75b9c3827fa3cfdb7efe2c4e05c3d13aefe1c825b9774a158"}}, {"data": {"id": "145923387e56933e7f6010786bc0738c770b4e5631640c2a1fb4702ff75b40ac", "source": "320c64ae7957fab2b92f45834b09f502a4a9dca20b16b4471cafbb3c479ba96e", "target": "21b6a798321a49f75b9c3827fa3cfdb7efe2c4e05c3d13aefe1c825b9774a158"}}, {"data": {"id": "335567536e593d8b5cdd68199de35e7254677f80307949ff3ee2fdcc3907c107", "source": "2ec74762990c76fb720f9c93872b9066e56928b1484c89d60b500e4be6a26574", "target": "21b6a798321a49f75b9c3827fa3cfdb7efe2c4e05c3d13aefe1c825b9774a158"}}, {"data": {"id": "b459688504934f821db1594801572aff29df21b5e77a8650fb532c6815c9eb31", "source": "46577bbdc25ef8658dcd6465951bc89d5d7326a461e43df8d0ff42b27f61d98c", "target": "21b6a798321a49f75b9c3827fa3cfdb7efe2c4e05c3d13aefe1c825b9774a158"}}, {"data": {"id": "974a2f20cfbe14af61a49de8a151688d2fdb9a09bde185bd96c0cc264a134b23", "source": "7c6b1c686ce84e854de71e324548966e1cd526b2a57d8b77e6ac63452ffd87d3", "target": "21b6a798321a49f75b9c3827fa3cfdb7efe2c4e05c3d13aefe1c825b9774a158"}}, {"data": {"id": "9d183653be147851a1165fc6fbfd75e764b496211df4e6a82433bc48fdd8b128", "source": "5b8f39054fe0c7e863376eea7ef1f02fec72f9ffe3383187004725921b521b84", "target": "21b6a798321a49f75b9c3827fa3cfdb7efe2c4e05c3d13aefe1c825b9774a158"}}, {"data": {"id": "eb51d61f991c80d5525faea50299d9875545f53a11318dd6c49c6369142c37de", "source": "b1141e0ba9ecac9c32e4cbe29ebcfbe6e9782d4735ec7e8ab9a8ee935ccc5f08", "target": "468ef0065ba2455fcf68a869e4922479423b4974f06645f8faf6fda629a7e37e"}}, {"data": {"id": "fd76eac1b9ae4ee38af78d15f616d173ff12d3eda57eec193fc64e7eb7e1ee06", "source": "5950c2d690b96aa41766ce98033b3df7b1db39eb6f6fdfde64fa7b8857d8da50", "target": "b1141e0ba9ecac9c32e4cbe29ebcfbe6e9782d4735ec7e8ab9a8ee935ccc5f08"}}, {"data": {"id": "3d369ccc46a7116382b9ee41c33ba7b8c71e3fbc878166fe5a9602106f19475f", "source": "aab01ebdcc700e43f43a775b36c90ccc28d095743d70eb9672b6320d424fc131", "target": "468ef0065ba2455fcf68a869e4922479423b4974f06645f8faf6fda629a7e37e"}}, {"data": {"id": "835c11b64bce95a40023cdaabf238774264c3d0e2321076025145d7e7c6f894e", "source": "c79bba4f6a73a3548585465aa9bb626268fb9e9d73ddb07c85f9d4bc490b6017", "target": "aab01ebdcc700e43f43a775b36c90ccc28d095743d70eb9672b6320d424fc131"}}, {"data": {"id": "6813ffda8ef7a5803e2d2a5a231ed46f6d5f6a08c4abd3e9f45bf88f197ac1a5", "source": "4ea0b317c36b2cf0a457d51b140193e477a17fc2dc44d52924a5fc0e50515438", "target": "aab01ebdcc700e43f43a775b36c90ccc28d095743d70eb9672b6320d424fc131"}}, {"data": {"id": "20d69fadec90dde97b8254e6c3f06f7cbc92b49a42ee69789ed808a0390e4705", "source": "55236c2756ace8d14a8838bc2462266027f68c056200770cd1e647d834f1d9f6", "target": "468ef0065ba2455fcf68a869e4922479423b4974f06645f8faf6fda629a7e37e"}}, {"data": {"id": "7bd07e7a7547ad0cba7f0d5e8f68a12efe4a241d942dbddb771bead023c0cf70", "source": "57f06c08351561e85771c51d991e1f8deea01f4077f033ec98ba402b8ec3d971", "target": "55236c2756ace8d14a8838bc2462266027f68c056200770cd1e647d834f1d9f6"}}, {"data": {"id": "4490d1c05e76bd633f3b7495f4568d79f0c0985000637ac07bb5f0757d0fab42", "source": "dc8ab306a30e4f957e469cbe4e231ba74230676c05e0034851215ef64ad4864f", "target": "468ef0065ba2455fcf68a869e4922479423b4974f06645f8faf6fda629a7e37e"}}, {"data": {"id": "59b12f36b1d5cda65babe4dc60eb25358211feecbebb03e6b8300b56c0eaed48", "source": "316d0a6276eaea2f62cdcb17c6a73a1035ae156ff437d899bc90e3529e0928df", "target": "dc8ab306a30e4f957e469cbe4e231ba74230676c05e0034851215ef64ad4864f"}}, {"data": {"id": "9fbd8de984edcaa63efccd5fc779415d747c044d58e4742f1bbb8bb1b71086b5", "source": "ec753afed0fd7de2a678563f5ad4cf0c8251d9cd1ed7fed115fef97584686caf", "target": "468ef0065ba2455fcf68a869e4922479423b4974f06645f8faf6fda629a7e37e"}}, {"data": {"id": "bd0368e75c9c82a0a81706fb19ede23d8023447fc627c50c39a155ed58b97292", "source": "88230214c5a9f3fbadcd92618a619fe106e627cc66fe9be7347f3c3e26e0e84d", "target": "ec753afed0fd7de2a678563f5ad4cf0c8251d9cd1ed7fed115fef97584686caf"}}, {"data": {"id": "ed803c2362d31d7fa81d64ceac44c6d546c24b947faebbdca07d6373cb9fae6f", "source": "07515d68646d454c3cc8ef5de976b88f8ff0d6d0f3ef0b18547d721e724220f8", "target": "468ef0065ba2455fcf68a869e4922479423b4974f06645f8faf6fda629a7e37e"}}]}}